ai2xlcore/__init__.py
ai2xlcore-0.0.1.dist-info/METADATA
ai2xlcore-0.0.1.dist-info/WHEEL
ai2xlcore-0.0.1.dist-info/top_level.txt
ai2xlcore-0.0.1.dist-info/RECORD
