Metadata-Version: 2.1
Name: ai2xlcore
Version: 0.0.1
Summary: ai2xl is a free Python library that allows using Excel for ML data preparation, zero dependency ML model deployment, model debugging, model explainability and collaboration.
Home-page: https://ai2xl.github.io
Author: ai2xl
Author-email: info@ai2xl.com
License: UNKNOWN
Platform: UNKNOWN
Requires-Dist: pandas
Requires-Dist: numpy
Requires-Dist: nyoka
Requires-Dist: py4j
Requires-Dist: python-dateutil
Requires-Dist: SciPy
Requires-Dist: scikit-learn
Requires-Dist: pandas-profiling
Requires-Dist: sweetviz
